{"metadata": {"dbt_schema_version": "https://schemas.getdbt.com/dbt/run-results/v4.json", "dbt_version": "1.0.5", "generated_at": "2022-04-21T21:55:15.330546Z", "invocation_id": "b5a1bfee-135e-4278-a69f-3edeb2f82b7b", "env": {}}, "results": [{"status": "success", "timing": [{"name": "compile", "started_at": "2022-04-21T21:55:12.940250Z", "completed_at": "2022-04-21T21:55:12.967376Z"}, {"name": "execute", "started_at": "2022-04-21T21:55:12.967733Z", "completed_at": "2022-04-21T21:55:13.708859Z"}], "thread_id": "Thread-2", "execution_time": 0.7693929672241211, "adapter_response": {"_message": "OK", "code": "CREATE VIEW"}, "message": "OK", "failures": null, "unique_id": "model.tnc_data_pipeline.conversion_goals_proc"}, {"status": "error", "timing": [], "thread_id": "Thread-1", "execution_time": 2.389566421508789, "adapter_response": {}, "message": "Database Error in model accounts_proc (models/admin/accounts_proc.sql)\n  Unrecognized name: store; Did you mean site? at [14:9]\n  compiled SQL at target/run/tnc_data_pipeline/models/admin/accounts_proc.sql", "failures": null, "unique_id": "model.tnc_data_pipeline.accounts_proc"}, {"status": "skipped", "timing": [], "thread_id": "Thread-4", "execution_time": 0.0, "adapter_response": {}, "message": null, "failures": null, "unique_id": "model.tnc_data_pipeline.fb_ads_insights"}], "elapsed_time": 2.8112032413482666, "args": {"write_json": true, "use_colors": true, "printer_width": 80, "version_check": true, "partial_parse": true, "static_parser": true, "profiles_dir": "/usr/src/develop/.dbt", "send_anonymous_usage_stats": true, "event_buffer_size": 100000, "vars": "{}\n", "which": "run", "rpc_method": "run", "indirect_selection": "eager"}}